hello_world/__init__.py
hello_world/print_hello.py
hello_print-0.0.1.dist-info/METADATA
hello_print-0.0.1.dist-info/WHEEL
hello_print-0.0.1.dist-info/top_level.txt
hello_print-0.0.1.dist-info/RECORD
