Metadata-Version: 2.1
Name: hello-print
Version: 0.0.1
Summary: print hello libary trial
Author: Movin Fernandes
Author-email: movin.fernandes@hotmail.com
Keywords: square,number,trial,test
